MANIFEST.in
README.rst
setup.py
gdrive_sync/__init__.py
gdrive_sync/__main__.py
gdrive_sync/change_db.py
gdrive_sync/configuration.py
gdrive_sync/gdrive_communication.py
gdrive_sync/gdrive_sync.py
gdrive_sync.egg-info/PKG-INFO
gdrive_sync.egg-info/SOURCES.txt
gdrive_sync.egg-info/dependency_links.txt
gdrive_sync.egg-info/requires.txt
gdrive_sync.egg-info/top_level.txt
scripts/gdrive_sync