Metadata-Version: 1.1
Name: gdrive-sync
Version: 0.5
Summary: Sync directories between your computer and Google Drive
Home-page: https://bitbucket.org/trlandet/gdrive_sync
Author: Tormod Landet
Author-email: UNKNOWN
License: UNKNOWN
Platform: UNKNOWN
Classifier: Development Status :: 4 - Beta
Classifier: Intended Audience :: End Users/Desktop
Classifier: License :: OSI Approved :: BSD License
Classifier: License :: OSI Approved :: GNU General Public License (GPL)
Classifier: License :: OSI Approved :: Python Software Foundation License
Classifier: Operating System :: OS Independent
Classifier: Programming Language :: Python :: 2.7
Classifier: Topic :: System :: Archiving :: Mirroring
Classifier: Topic :: Software Development :: Libraries :: Python Modules
Classifier: Environment :: Console
